{
  "aws_cdk.aws_pinpointemail-1.204.0-py3-none-any.whl": {
    "status": "pending",
    "sha256": "3c852a7c7f4e1f115baee75e9c73fa108b051804cecdb8353b890f9e8703fb1c",
    "dependencies": {
      "required": [
        "aws-cdk.core",
        "constructs",
        "jsii",
        "publication",
        "typeguard"
      ]
    },
    "original_requirements": [
      "aws-cdk.core (==1.204.0)",
      "constructs (<4.0.0,>=3.3.69)",
      "jsii (<2.0.0,>=1.84.0)",
      "publication (>=0.0.3)",
      "typeguard (~=2.13.3)"
    ]
  },
  "aws_cdk.aws_pinpointemail-1.203.0-py3-none-any.whl": {
    "status": "pending",
    "sha256": "89f9edc03dc371377c18c50848c04daa7e0a684a8683b98964abd6ce6f792d7d",
    "dependencies": {
      "required": [
        "aws-cdk.core",
        "constructs",
        "jsii",
        "publication",
        "typeguard"
      ]
    },
    "original_requirements": [
      "aws-cdk.core (==1.203.0)",
      "constructs (<4.0.0,>=3.3.69)",
      "jsii (<2.0.0,>=1.74.0)",
      "publication (>=0.0.3)",
      "typeguard (~=2.13.3)"
    ]
  },
  "aws_cdk.aws_pinpointemail-1.202.0-py3-none-any.whl": {
    "status": "pending",
    "sha256": "450f17968508d1665593d7381ff936af636288e2b221d402276c9851f426d837",
    "dependencies": {
      "required": [
        "aws-cdk.core",
        "constructs",
        "jsii",
        "publication",
        "typeguard"
      ]
    },
    "original_requirements": [
      "aws-cdk.core (==1.202.0)",
      "constructs (<4.0.0,>=3.3.69)",
      "jsii (<2.0.0,>=1.74.0)",
      "publication (>=0.0.3)",
      "typeguard (~=2.13.3)"
    ]
  },
  "aws_cdk.aws_pinpointemail-1.201.0-py3-none-any.whl": {
    "status": "pending",
    "sha256": "2f72d29ce696f52d25253b22d60ad92b6a4e2c79659b9efc7b42f36949cb19c8",
    "dependencies": {
      "required": [
        "aws-cdk.core",
        "constructs",
        "jsii",
        "publication",
        "typeguard"
      ]
    },
    "original_requirements": [
      "aws-cdk.core (==1.201.0)",
      "constructs (<4.0.0,>=3.3.69)",
      "jsii (<2.0.0,>=1.74.0)",
      "publication (>=0.0.3)",
      "typeguard (~=2.13.3)"
    ]
  },
  "aws_cdk.aws_pinpointemail-1.200.0-py3-none-any.whl": {
    "status": "pending",
    "sha256": "292a6d88b9055aaa480365581bbad3d9e3048d41066ac2efcb682e35c7e1d724",
    "dependencies": {
      "required": [
        "aws-cdk.core",
        "constructs",
        "jsii",
        "publication",
        "typeguard"
      ]
    },
    "original_requirements": [
      "aws-cdk.core (==1.200.0)",
      "constructs (<4.0.0,>=3.3.69)",
      "jsii (<2.0.0,>=1.74.0)",
      "publication (>=0.0.3)",
      "typeguard (~=2.13.3)"
    ]
  }
}