{
  "mlserver-1.7.1-py3-none-any.whl": {
    "status": "pending",
    "sha256": "d2ac7502915bb5311343a878aa1fb614f9b0f2436ee550a6137c1872a4dca193",
    "dependencies": {
      "required": [
        "aiofiles",
        "aiokafka",
        "click",
        "fastapi",
        "gevent",
        "geventhttpclient",
        "grpcio",
        "importlib-resources",
        "numpy",
        "opentelemetry-exporter-otlp-proto-grpc",
        "opentelemetry-instrumentation-fastapi",
        "opentelemetry-instrumentation-grpc",
        "opentelemetry-sdk",
        "orjson",
        "pandas",
        "protobuf",
        "py-grpc-prometheus",
        "pydantic",
        "pydantic-settings",
        "python-dotenv",
        "python-multipart",
        "starlette-exporter",
        "tritonclient",
        "uvicorn",
        "uvloop"
      ]
    },
    "original_requirements": [
      "aiofiles",
      "aiokafka",
      "click",
      "fastapi (>=0.88.0,!=0.89.0,<0.116.0)",
      "gevent",
      "geventhttpclient",
      "grpcio (>=1.67.1)",
      "importlib-resources (>=5.12,<7.0)",
      "numpy",
      "opentelemetry-exporter-otlp-proto-grpc (>=1.22.0,<2.0.0)",
      "opentelemetry-instrumentation-fastapi (>=0.43b0)",
      "opentelemetry-instrumentation-grpc (>=0.43b0)",
      "opentelemetry-sdk (>=1.22.0,<2.0.0)",
      "orjson",
      "pandas",
      "protobuf (>=5.27.2,<7.0.0)",
      "py-grpc-prometheus",
      "pydantic (>=2.7.1,<3.0.0)",
      "pydantic-settings (>=2.3.0,<3.0.0)",
      "python-dotenv",
      "python-multipart",
      "starlette-exporter",
      "tritonclient[http] (>=2.42)",
      "uvicorn",
      "uvloop ; sys_platform != \"win32\" and sys_platform != \"cygwin\" and platform_python_implementation != \"PyPy\""
    ]
  },
  "mlserver-1.7.0-py3-none-any.whl": {
    "status": "pending",
    "sha256": "3c852da377e158a4affa426a79aaabf3a8b523ad88739be656b24fcc7b6ba742",
    "dependencies": {
      "required": [
        "aiofiles",
        "aiokafka",
        "click",
        "fastapi",
        "gevent",
        "geventhttpclient",
        "grpcio",
        "importlib-resources",
        "numpy",
        "opentelemetry-exporter-otlp-proto-grpc",
        "opentelemetry-instrumentation-fastapi",
        "opentelemetry-instrumentation-grpc",
        "opentelemetry-sdk",
        "orjson",
        "pandas",
        "protobuf",
        "py-grpc-prometheus",
        "pydantic",
        "pydantic-settings",
        "python-dotenv",
        "python-multipart",
        "starlette-exporter",
        "tritonclient",
        "uvicorn",
        "uvloop"
      ]
    },
    "original_requirements": [
      "aiofiles",
      "aiokafka",
      "click",
      "fastapi (>=0.88.0,!=0.89.0,<0.116.0)",
      "gevent",
      "geventhttpclient",
      "grpcio",
      "importlib-resources (>=5.12,<7.0)",
      "numpy",
      "opentelemetry-exporter-otlp-proto-grpc (>=1.22.0,<2.0.0)",
      "opentelemetry-instrumentation-fastapi (>=0.43b0)",
      "opentelemetry-instrumentation-grpc (>=0.43b0)",
      "opentelemetry-sdk (>=1.22.0,<2.0.0)",
      "orjson",
      "pandas",
      "protobuf",
      "py-grpc-prometheus",
      "pydantic (>=2.7.1,<3.0.0)",
      "pydantic-settings (>=2.3.0,<3.0.0)",
      "python-dotenv",
      "python-multipart",
      "starlette-exporter",
      "tritonclient[http] (>=2.42)",
      "uvicorn",
      "uvloop ; sys_platform != \"win32\" and sys_platform != \"cygwin\" and platform_python_implementation != \"PyPy\""
    ]
  },
  "mlserver-1.6.1-py3-none-any.whl": {
    "status": "pending",
    "sha256": "3226b7f107d2fbe149f79df49cb07e694261a8200ef269c4673db324778cffed",
    "dependencies": {
      "required": [
        "aiofiles",
        "aiokafka",
        "click",
        "fastapi",
        "gevent",
        "geventhttpclient",
        "grpcio",
        "importlib-resources",
        "numpy",
        "opentelemetry-exporter-otlp-proto-grpc",
        "opentelemetry-instrumentation-fastapi",
        "opentelemetry-instrumentation-grpc",
        "opentelemetry-sdk",
        "orjson",
        "pandas",
        "protobuf",
        "py-grpc-prometheus",
        "pydantic",
        "pydantic-settings",
        "python-dotenv",
        "python-multipart",
        "starlette-exporter",
        "tritonclient",
        "uvicorn",
        "uvloop"
      ]
    },
    "original_requirements": [
      "aiofiles",
      "aiokafka",
      "click",
      "fastapi (>=0.88.0,!=0.89.0,<=0.110.0)",
      "gevent",
      "geventhttpclient",
      "grpcio",
      "importlib-resources (>=5.12,<7.0)",
      "numpy",
      "opentelemetry-exporter-otlp-proto-grpc (>=1.22.0,<2.0.0)",
      "opentelemetry-instrumentation-fastapi (>=0.43b0)",
      "opentelemetry-instrumentation-grpc (>=0.43b0)",
      "opentelemetry-sdk (>=1.22.0,<2.0.0)",
      "orjson",
      "pandas",
      "protobuf",
      "py-grpc-prometheus",
      "pydantic (==2.7.1)",
      "pydantic-settings (==2.2.1)",
      "python-dotenv",
      "python-multipart",
      "starlette-exporter",
      "tritonclient[http] (>=2.42)",
      "uvicorn",
      "uvloop ; (sys_platform != \"win32\" and sys_platform != \"cygwin\") and platform_python_implementation != \"PyPy\""
    ]
  },
  "mlserver-1.6.0-py3-none-any.whl": {
    "status": "pending",
    "sha256": "132fffc91c9d2470abea9993d362fdff66c0dcfc6e5daaf1f822a006588662ca",
    "dependencies": {
      "required": [
        "aiofiles",
        "aiokafka",
        "click",
        "fastapi",
        "gevent",
        "geventhttpclient",
        "grpcio",
        "importlib-resources",
        "numpy",
        "opentelemetry-exporter-otlp-proto-grpc",
        "opentelemetry-instrumentation-fastapi",
        "opentelemetry-instrumentation-grpc",
        "opentelemetry-sdk",
        "orjson",
        "pandas",
        "protobuf",
        "py-grpc-prometheus",
        "pydantic",
        "pydantic-settings",
        "python-dotenv",
        "python-multipart",
        "starlette-exporter",
        "tritonclient",
        "uvicorn",
        "uvloop"
      ]
    },
    "original_requirements": [
      "aiofiles",
      "aiokafka",
      "click",
      "fastapi (>=0.88.0,!=0.89.0,<=0.110.0)",
      "gevent",
      "geventhttpclient",
      "grpcio",
      "importlib-resources (>=5.12,<7.0)",
      "numpy",
      "opentelemetry-exporter-otlp-proto-grpc (>=1.22.0,<2.0.0)",
      "opentelemetry-instrumentation-fastapi (>=0.43b0)",
      "opentelemetry-instrumentation-grpc (>=0.43b0)",
      "opentelemetry-sdk (>=1.22.0,<2.0.0)",
      "orjson",
      "pandas",
      "protobuf",
      "py-grpc-prometheus",
      "pydantic (==2.7.1)",
      "pydantic-settings (==2.2.1)",
      "python-dotenv",
      "python-multipart",
      "starlette-exporter",
      "tritonclient[http] (>=2.42)",
      "uvicorn",
      "uvloop ; (sys_platform != \"win32\" and sys_platform != \"cygwin\") and platform_python_implementation != \"PyPy\""
    ]
  },
  "mlserver-1.5.0-py3-none-any.whl": {
    "status": "pending",
    "sha256": "4ac97feade88aa34d4a40929267edf56688f14de45f54327a48091afe443d624",
    "dependencies": {
      "required": [
        "aiofiles",
        "aiokafka",
        "click",
        "fastapi",
        "gevent",
        "geventhttpclient",
        "grpcio",
        "importlib-resources",
        "numpy",
        "opentelemetry-exporter-otlp-proto-grpc",
        "opentelemetry-instrumentation-fastapi",
        "opentelemetry-instrumentation-grpc",
        "opentelemetry-sdk",
        "orjson",
        "pandas",
        "protobuf",
        "py-grpc-prometheus",
        "pydantic",
        "python-dotenv",
        "python-multipart",
        "starlette-exporter",
        "tritonclient",
        "uvicorn",
        "uvloop"
      ]
    },
    "original_requirements": [
      "aiofiles",
      "aiokafka",
      "click",
      "fastapi (>=0.88.0,!=0.89.0,<=0.110.0)",
      "gevent",
      "geventhttpclient",
      "grpcio",
      "importlib-resources (>=5.12.0,<6.0.0)",
      "numpy",
      "opentelemetry-exporter-otlp-proto-grpc (>=1.22.0,<2.0.0)",
      "opentelemetry-instrumentation-fastapi (>=0.43b0)",
      "opentelemetry-instrumentation-grpc (>=0.43b0)",
      "opentelemetry-sdk (>=1.22.0,<2.0.0)",
      "orjson",
      "pandas",
      "protobuf",
      "py-grpc-prometheus",
      "pydantic (<2.0.0)",
      "python-dotenv",
      "python-multipart",
      "starlette-exporter",
      "tritonclient[http] (>=2.42)",
      "uvicorn",
      "uvloop ; (sys_platform != \"win32\" and sys_platform != \"cygwin\") and platform_python_implementation != \"PyPy\""
    ]
  }
}