{
  "mosestokenizer-1.0.0-py3-none-any.whl": {
    "status": "pending",
    "sha256": "4de94102c00ad21ea26c1d8327bf72d38288c6c83c9b2920fb9a86c66eddf8b7",
    "dependencies": {
      "required": [
        "docopt",
        "openfile",
        "toolwrapper"
      ]
    },
    "original_requirements": [
      "docopt",
      "openfile",
      "toolwrapper"
    ]
  },
  "mosestokenizer-0.5.0-py3-none-any.whl": {
    "status": "pending",
    "sha256": "e050a2c4a9114f1f11043532aeb2ce091f2b8da613a3007be117d1122a2c92db",
    "dependencies": {
      "required": [
        "docopt",
        "openfile",
        "toolwrapper"
      ]
    },
    "original_requirements": [
      "docopt",
      "openfile",
      "toolwrapper"
    ]
  },
  "mosestokenizer-0.3.0-py3-none-any.whl": {
    "status": "pending",
    "sha256": "923adc38d209dd5b482dd3e2eb3baccfa9988c4d018b7ae9d3357a11de8655dc",
    "dependencies": {
      "required": [
        "docopt",
        "openfile",
        "toolwrapper"
      ]
    },
    "original_requirements": [
      "docopt",
      "openfile",
      "toolwrapper"
    ]
  }
}