{
  "mypy_boto3_amp-1.42.3-py3-none-any.whl": {
    "status": "pending",
    "sha256": "d41221ec79306fb63f688e729f1526142c52fcaa8d0c706520ba4b4bcfebb5db",
    "dependencies": {
      "required": [
        "typing-extensions"
      ]
    },
    "original_requirements": [
      "typing-extensions; python_version < \"3.12\""
    ]
  },
  "mypy_boto3_amp-1.41.0-py3-none-any.whl": {
    "status": "pending",
    "sha256": "b93e65f7ad09df3cb0b3b99ed064eebeaf521732a1df0381a3f94047dcfd0014",
    "dependencies": {
      "required": [
        "typing-extensions"
      ]
    },
    "original_requirements": [
      "typing-extensions; python_version < \"3.12\""
    ]
  },
  "mypy_boto3_amp-1.40.72-py3-none-any.whl": {
    "status": "pending",
    "sha256": "8c92d4c5f78d19248091456cd9f834c0493be8e96fb4dce49b8c1f4e40fc1e77",
    "dependencies": {
      "required": [
        "typing-extensions"
      ]
    },
    "original_requirements": [
      "typing-extensions; python_version < \"3.12\""
    ]
  },
  "mypy_boto3_amp-1.40.63-py3-none-any.whl": {
    "status": "pending",
    "sha256": "148223cfa5f7e1c21672853e32f25eb923d2c5ad3ceb963ae8e90d444b0b2fb9",
    "dependencies": {
      "required": [
        "typing-extensions"
      ]
    },
    "original_requirements": [
      "typing-extensions; python_version < \"3.12\""
    ]
  },
  "mypy_boto3_amp-1.40.55-py3-none-any.whl": {
    "status": "pending",
    "sha256": "8c644aee8792b57713ace5ee577716d8a5e8616f13f4a481c6f058cd9888c8ae",
    "dependencies": {
      "required": [
        "typing-extensions"
      ]
    },
    "original_requirements": [
      "typing-extensions; python_version < \"3.12\""
    ]
  }
}