{
  "mypy_boto3_route53domains-1.42.3-py3-none-any.whl": {
    "status": "pending",
    "sha256": "20f3982dc14d5cdd720816c6d8d64e198f426d44fadab19332e8b5823d245bb8",
    "dependencies": {
      "required": [
        "typing-extensions"
      ]
    },
    "original_requirements": [
      "typing-extensions; python_version < \"3.12\""
    ]
  },
  "mypy_boto3_route53domains-1.41.0-py3-none-any.whl": {
    "status": "pending",
    "sha256": "2c81fbad7c4e281da27de1f41b0251e1ff420a70c2f7b382b570f129901367a7",
    "dependencies": {
      "required": [
        "typing-extensions"
      ]
    },
    "original_requirements": [
      "typing-extensions; python_version < \"3.12\""
    ]
  },
  "mypy_boto3_route53domains-1.40.59-py3-none-any.whl": {
    "status": "pending",
    "sha256": "76f56464f84b42bfedd62a992c0e4a8cec33ee81e6075b7fe9387171b560bd95",
    "dependencies": {
      "required": [
        "typing-extensions"
      ]
    },
    "original_requirements": [
      "typing-extensions; python_version < \"3.12\""
    ]
  },
  "mypy_boto3_route53domains-1.40.23-py3-none-any.whl": {
    "status": "pending",
    "sha256": "7c76e5dc6388fa152984027ff798974b92412004856d39961bea5b52c87e23d4",
    "dependencies": {
      "required": [
        "typing-extensions"
      ]
    },
    "original_requirements": [
      "typing-extensions; python_version < \"3.12\""
    ]
  },
  "mypy_boto3_route53domains-1.40.20-py3-none-any.whl": {
    "status": "pending",
    "sha256": "f91bf1f828429a9a99ba5546cc62daa5c7a116e2f43026906e627274b415451b",
    "dependencies": {
      "required": [
        "typing-extensions"
      ]
    },
    "original_requirements": [
      "typing-extensions; python_version < \"3.12\""
    ]
  }
}