{
  "types_aiobotocore_kendra_ranking-3.0.0-py3-none-any.whl": {
    "status": "pending",
    "sha256": "d31fa982dcd9bab9f76b08a76dd5ace6ccb1258147b5d72329e88639136b60c2",
    "dependencies": {
      "required": [
        "typing-extensions"
      ]
    },
    "original_requirements": [
      "typing-extensions; python_version < \"3.12\""
    ]
  },
  "types_aiobotocore_kendra_ranking-2.26.0-py3-none-any.whl": {
    "status": "pending",
    "sha256": "6b9b47e3c35bb7862b7f7af719b1e226204493412ded921ac12d5bd0ea2e53c1",
    "dependencies": {
      "required": [
        "typing-extensions"
      ]
    },
    "original_requirements": [
      "typing-extensions; python_version < \"3.12\""
    ]
  },
  "types_aiobotocore_kendra_ranking-2.25.2-py3-none-any.whl": {
    "status": "pending",
    "sha256": "519c9079e04da2b7cf20ecd1b1b56fa3a2824a96c2546e17bec67dedc28e9112",
    "dependencies": {
      "required": [
        "typing-extensions"
      ]
    },
    "original_requirements": [
      "typing-extensions; python_version < \"3.12\""
    ]
  },
  "types_aiobotocore_kendra_ranking-2.25.1-py3-none-any.whl": {
    "status": "pending",
    "sha256": "571d23709361640032e9a6b3870b3809d1f5a9cf65155bacab3cc11d97386bee",
    "dependencies": {
      "required": [
        "typing-extensions"
      ]
    },
    "original_requirements": [
      "typing-extensions; python_version < \"3.12\""
    ]
  },
  "types_aiobotocore_kendra_ranking-2.25.0-py3-none-any.whl": {
    "status": "pending",
    "sha256": "c60f6f9f0080b6e8372b4c02c3c20857d9cf434af879dcedec0bd3e9d40fa6cd",
    "dependencies": {
      "required": [
        "typing-extensions"
      ]
    },
    "original_requirements": [
      "typing-extensions; python_version < \"3.12\""
    ]
  }
}