{
  "types_boto3_ram-1.42.3-py3-none-any.whl": {
    "status": "pending",
    "sha256": "8a2ae32b5434a3b409cc0393b23457e4ca45aa4096d5a6c8475cec3ce1678d5e",
    "dependencies": {
      "required": [
        "typing-extensions"
      ]
    },
    "original_requirements": [
      "typing-extensions; python_version < \"3.12\""
    ]
  },
  "types_boto3_ram-1.41.0-py3-none-any.whl": {
    "status": "pending",
    "sha256": "6db16487317a9f09192e833218f9e95dfde92297423552ce8e2dd770f3d6d0f8",
    "dependencies": {
      "required": [
        "typing-extensions"
      ]
    },
    "original_requirements": [
      "typing-extensions; python_version < \"3.12\""
    ]
  },
  "types_boto3_ram-1.40.61-py3-none-any.whl": {
    "status": "pending",
    "sha256": "0a930f46e2cb5f26af4747509cd6fd8612d7b5608f737f64bc044756d5723023",
    "dependencies": {
      "required": [
        "typing-extensions"
      ]
    },
    "original_requirements": [
      "typing-extensions; python_version < \"3.12\""
    ]
  },
  "types_boto3_ram-1.40.18-py3-none-any.whl": {
    "status": "pending",
    "sha256": "f73a6be3b20752219df8b307e98bae84450f28ad1a0c143644a6aca086e5117c",
    "dependencies": {
      "required": [
        "typing-extensions"
      ]
    },
    "original_requirements": [
      "typing-extensions; python_version < \"3.12\""
    ]
  },
  "types_boto3_ram-1.40.0-py3-none-any.whl": {
    "status": "pending",
    "sha256": "8bb7916e89929a16e918d327df573379fbeb32929f794092a42df7bec3716e29",
    "dependencies": {
      "required": [
        "typing-extensions"
      ]
    },
    "original_requirements": [
      "typing-extensions; python_version < \"3.12\""
    ]
  }
}