{
  "types_boto3_application_signals-1.42.3-py3-none-any.whl": {
    "status": "pending",
    "sha256": "a0a32a7795f56edd86bd90352683b2df727357942e6e1f513becc9f90f13befc",
    "dependencies": {
      "required": [
        "typing-extensions"
      ]
    },
    "original_requirements": [
      "typing-extensions; python_version < \"3.12\""
    ]
  },
  "types_boto3_application_signals-1.41.1-py3-none-any.whl": {
    "status": "pending",
    "sha256": "7ddc9996a95dcade4ce80aedd45e5df573073d49715a740ccd5a50c16d7393cb",
    "dependencies": {
      "required": [
        "typing-extensions"
      ]
    },
    "original_requirements": [
      "typing-extensions; python_version < \"3.12\""
    ]
  },
  "types_boto3_application_signals-1.41.0-py3-none-any.whl": {
    "status": "pending",
    "sha256": "93393db04b7696430bf9c542572b70e76f0a4d32000c123df73ad953d301090c",
    "dependencies": {
      "required": [
        "typing-extensions"
      ]
    },
    "original_requirements": [
      "typing-extensions; python_version < \"3.12\""
    ]
  },
  "types_boto3_application_signals-1.40.61-py3-none-any.whl": {
    "status": "pending",
    "sha256": "f313cf98e8de07959a19e41b020757f1f29e49b010d69346a5898f03978f3f66",
    "dependencies": {
      "required": [
        "typing-extensions"
      ]
    },
    "original_requirements": [
      "typing-extensions; python_version < \"3.12\""
    ]
  },
  "types_boto3_application_signals-1.40.59-py3-none-any.whl": {
    "status": "pending",
    "sha256": "0a376262be089ad09e1f69a49f2873cd1da4165033ed61177bbf5e6a432fb490",
    "dependencies": {
      "required": [
        "typing-extensions"
      ]
    },
    "original_requirements": [
      "typing-extensions; python_version < \"3.12\""
    ]
  }
}