{
  "types_boto3_cloudfront_keyvaluestore-1.42.3-py3-none-any.whl": {
    "status": "pending",
    "sha256": "e57595bc03f9d93a7742c8a4e8d4061df10c05c119d08e2d0eeabe69fb88c561",
    "dependencies": {
      "required": [
        "typing-extensions"
      ]
    },
    "original_requirements": [
      "typing-extensions; python_version < \"3.12\""
    ]
  },
  "types_boto3_cloudfront_keyvaluestore-1.41.0-py3-none-any.whl": {
    "status": "pending",
    "sha256": "c4d33e0bd54142fa06c888da48d5e8e26e138bb1fa08474fa461c6a2a01619cc",
    "dependencies": {
      "required": [
        "typing-extensions"
      ]
    },
    "original_requirements": [
      "typing-extensions; python_version < \"3.12\""
    ]
  },
  "types_boto3_cloudfront_keyvaluestore-1.40.55-py3-none-any.whl": {
    "status": "pending",
    "sha256": "f418fb65cc12100331518d847af58d4ac0068af167188313988ecf647bcada83",
    "dependencies": {
      "required": [
        "typing-extensions"
      ]
    },
    "original_requirements": [
      "typing-extensions; python_version < \"3.12\""
    ]
  },
  "types_boto3_cloudfront_keyvaluestore-1.40.0-py3-none-any.whl": {
    "status": "pending",
    "sha256": "550c1bdd4891fb6ad66d2489d228ac777969356189c2ad32d455824ee2f14976",
    "dependencies": {
      "required": [
        "typing-extensions"
      ]
    },
    "original_requirements": [
      "typing-extensions; python_version < \"3.12\""
    ]
  },
  "types_boto3_cloudfront_keyvaluestore-1.39.0-py3-none-any.whl": {
    "status": "pending",
    "sha256": "dae912107f6d8d8068870cba75ae1e968529ba315a090b4ab357a7a5d4537099",
    "dependencies": {
      "required": [
        "typing-extensions"
      ]
    },
    "original_requirements": [
      "typing-extensions; python_version < \"3.12\""
    ]
  }
}