{
  "types_boto3_chime-1.42.3-py3-none-any.whl": {
    "status": "pending",
    "sha256": "6b7801c0704e2ceeff0a11d0274db94557891cfcc86eebfcbe006f374d0be167",
    "dependencies": {
      "required": [
        "typing-extensions"
      ]
    },
    "original_requirements": [
      "typing-extensions; python_version < \"3.12\""
    ]
  },
  "types_boto3_chime-1.41.0-py3-none-any.whl": {
    "status": "pending",
    "sha256": "dc48d0ed0653289255ed4656f3d02c3698c1ec0d1fe7157fdd210af1d1605be4",
    "dependencies": {
      "required": [
        "typing-extensions"
      ]
    },
    "original_requirements": [
      "typing-extensions; python_version < \"3.12\""
    ]
  },
  "types_boto3_chime-1.40.63-py3-none-any.whl": {
    "status": "pending",
    "sha256": "c3a5f1bbcd3ab5407efa60c0b7d558b6f50316f05ce00cc782d07b5297f8faea",
    "dependencies": {
      "required": [
        "typing-extensions"
      ]
    },
    "original_requirements": [
      "typing-extensions; python_version < \"3.12\""
    ]
  },
  "types_boto3_chime-1.40.19-py3-none-any.whl": {
    "status": "pending",
    "sha256": "fc3ee5bcd2e593a0cf06ed28db48b00754a0592837309d14b13c4c98c6fd74eb",
    "dependencies": {
      "required": [
        "typing-extensions"
      ]
    },
    "original_requirements": [
      "typing-extensions; python_version < \"3.12\""
    ]
  },
  "types_boto3_chime-1.40.0-py3-none-any.whl": {
    "status": "pending",
    "sha256": "04d6549b5b4a002184c87537c59c52b3919056b6ffacc9d4a032d8a5aaf83b06",
    "dependencies": {
      "required": [
        "typing-extensions"
      ]
    },
    "original_requirements": [
      "typing-extensions; python_version < \"3.12\""
    ]
  }
}